odoo/addons/product_template_multi_link_date_span/README.rst
odoo/addons/product_template_multi_link_date_span/__init__.py
odoo/addons/product_template_multi_link_date_span/__manifest__.py
odoo/addons/product_template_multi_link_date_span/i18n/es.po
odoo/addons/product_template_multi_link_date_span/i18n/es_AR.po
odoo/addons/product_template_multi_link_date_span/i18n/it.po
odoo/addons/product_template_multi_link_date_span/i18n/product_template_multi_link_date_span.pot
odoo/addons/product_template_multi_link_date_span/i18n/pt_BR.po
odoo/addons/product_template_multi_link_date_span/models/__init__.py
odoo/addons/product_template_multi_link_date_span/models/product_template_link.py
odoo/addons/product_template_multi_link_date_span/models/product_template_link_type.py
odoo/addons/product_template_multi_link_date_span/readme/CONTRIBUTORS.md
odoo/addons/product_template_multi_link_date_span/readme/CREDITS.md
odoo/addons/product_template_multi_link_date_span/readme/DESCRIPTION.md
odoo/addons/product_template_multi_link_date_span/static/description/icon.png
odoo/addons/product_template_multi_link_date_span/static/description/index.html
odoo/addons/product_template_multi_link_date_span/tests/__init__.py
odoo/addons/product_template_multi_link_date_span/tests/test_product_template_link_date_span.py
odoo/addons/product_template_multi_link_date_span/views/product_template_link_type_view.xml
odoo/addons/product_template_multi_link_date_span/views/product_template_link_view.xml
odoo_addon_product_template_multi_link_date_span-18.0.1.0.0.5.dist-info/METADATA
odoo_addon_product_template_multi_link_date_span-18.0.1.0.0.5.dist-info/WHEEL
odoo_addon_product_template_multi_link_date_span-18.0.1.0.0.5.dist-info/top_level.txt
odoo_addon_product_template_multi_link_date_span-18.0.1.0.0.5.dist-info/RECORD
