Metadata-Version: 2.1
Name: odoo-addon-product_template_multi_link_date_span
Version: 18.0.1.0.0.5
Requires-Python: >=3.10
Requires-Dist: odoo-addon-product_template_multi_link==18.0.*
Requires-Dist: odoo==18.0.*
Summary: Add an optional date span for when a link is active.
Home-page: https://github.com/OCA/e-commerce
License: AGPL-3
Author: Camptocamp, Odoo Community Association (OCA)
Author-email: support@odoo-community.org
Classifier: Programming Language :: Python
Classifier: Framework :: Odoo
Classifier: Framework :: Odoo :: 18.0
Classifier: License :: OSI Approved :: GNU Affero General Public License v3
